emailverifier/__init__.py
emailverifier/client.py
emailverifier/version.py
emailverifier/exceptions/__init__.py
emailverifier/exceptions/api_base_exception.py
emailverifier/exceptions/general_exception.py
emailverifier/exceptions/http_exception.py
emailverifier/exceptions/invalid_argument_exception.py
emailverifier/exceptions/undefined_variable_exception.py
emailverifier/models/__init__.py
emailverifier/models/audit.py
emailverifier/models/response.py
email_verifier-1.0.0.dist-info/LICENSE
email_verifier-1.0.0.dist-info/METADATA
email_verifier-1.0.0.dist-info/WHEEL
email_verifier-1.0.0.dist-info/top_level.txt
email_verifier-1.0.0.dist-info/RECORD
