Metadata-Version: 2.1
Name: email-verifier
Version: 1.0.0
Summary: Python client library for Email Verification API.
Home-page: https://github.com/whois-api-llc/python-email-verifier
Author: Whois API, Inc.
Author-email: support@whoisxmlapi.com
License: MIT License
Keywords: email,verification,email verifier,api,email verification api
Platform: UNKNOWN
Classifier: Development Status :: 5 - Production/Stable
Classifier: Intended Audience :: Developers
Classifier: License :: OSI Approved :: MIT License
Classifier: Operating System :: Unix
Classifier: Operating System :: POSIX
Classifier: Operating System :: Microsoft :: Windows
Classifier: Programming Language :: Python
Classifier: Programming Language :: Python :: 2.7
Classifier: Programming Language :: Python :: 3
Classifier: Programming Language :: Python :: 3.6
Classifier: Programming Language :: Python :: Implementation :: CPython
Classifier: Topic :: Utilities
Provides-Extra: dev
